{"experiments":{"hotfix-disable-websockets-over-h2-65-1523978":{"branch":"disabled","expired":false,"lastSeen":"2019-02-15T11:33:35.686Z","preferences":{"network.http.spdy.websockets":{"preferenceBranchType":"default","preferenceType":"boolean","preferenceValue":false,"previousPreferenceValue":true}},"experimentType":"exp","actionName":"SinglePreferenceExperimentAction","slug":"hotfix-disable-websockets-over-h2-65-1523978"},"prefflip-push-performance-1491171":{"branch":"control","expired":false,"lastSeen":"2019-02-15T11:33:35.687Z","preferences":{"dom.push.alwaysConnect":{"preferenceBranchType":"default","preferenceType":"boolean","preferenceValue":false,"previousPreferenceValue":null}},"experimentType":"exp","actionName":"SinglePreferenceExperimentAction","slug":"prefflip-push-performance-1491171"}}}